hayley_demo/__init__.py
hayley_demo/main.py
hayley_demo-0.1.1.dist-info/LICENSE
hayley_demo-0.1.1.dist-info/METADATA
hayley_demo-0.1.1.dist-info/WHEEL
hayley_demo-0.1.1.dist-info/top_level.txt
hayley_demo-0.1.1.dist-info/RECORD
