Metadata-Version: 2.1
Name: hayley_demo
Version: 0.1.1
Summary: Short description for hayley project.
Home-page: 
Author: Hayley Wu
Author-email: Hayley.Wu@dell.com
License: MIT
Classifier: License :: OSI Approved :: MIT License
Classifier: Programming Language :: Python
Classifier: Programming Language :: Python :: 3
Classifier: Programming Language :: Python :: 3.6
Classifier: Programming Language :: Python :: Implementation :: CPython
Classifier: Programming Language :: Python :: Implementation :: PyPy
Requires-Python: >=3.6.0
License-File: LICENSE
